RESTArt_WeChat-0.1.0.dist-info/WHEEL
RESTArt_WeChat-0.1.0.dist-info/RECORD
RESTArt_WeChat-0.1.0.dist-info/METADATA
RESTArt_WeChat-0.1.0.dist-info/metadata.json
RESTArt_WeChat-0.1.0.dist-info/top_level.txt
RESTArt_WeChat-0.1.0.dist-info/DESCRIPTION.rst
restart_wechat/interface.py
restart_wechat/__init__.py
restart_wechat/wechat.py
restart_wechat/config.py
