Metadata-Version: 2.0
Name: RESTArt-WeChat
Version: 0.1.0
Summary: A RESTArt extension for WeChat Media Platform development.
Home-page: https://github.com/RussellLuo/restart-wechat
Author: RussellLuo
Author-email: luopeng.he@gmail.com
License: MIT
Keywords: WeChat,RESTArt,Python
Platform: UNKNOWN
Requires-Dist: python-restart
Requires-Dist: wechatpy
Requires-Dist: cryptography
